thousandeyes_sdk/bgp_monitors/__init__.py
thousandeyes_sdk/bgp_monitors/py.typed
thousandeyes_sdk/bgp_monitors/api/__init__.py
thousandeyes_sdk/bgp_monitors/api/bgp_monitors_api.py
thousandeyes_sdk/bgp_monitors/models/__init__.py
thousandeyes_sdk/bgp_monitors/models/error.py
thousandeyes_sdk/bgp_monitors/models/link.py
thousandeyes_sdk/bgp_monitors/models/monitor.py
thousandeyes_sdk/bgp_monitors/models/monitor_type.py
thousandeyes_sdk/bgp_monitors/models/monitors.py
thousandeyes_sdk/bgp_monitors/models/self_links.py
thousandeyes_sdk/bgp_monitors/models/unauthorized_error.py
thousandeyes_sdk_bgp_monitors-2.23.0.dist-info/licenses/LICENSE
thousandeyes_sdk_bgp_monitors-2.23.0.dist-info/licenses/NOTICE
thousandeyes_sdk_bgp_monitors-2.23.0.dist-info/METADATA
thousandeyes_sdk_bgp_monitors-2.23.0.dist-info/WHEEL
thousandeyes_sdk_bgp_monitors-2.23.0.dist-info/top_level.txt
thousandeyes_sdk_bgp_monitors-2.23.0.dist-info/RECORD
